tgstk/__init__.py
tgstk/_tgstk.pyd
tgstk/libgmp-10.dll
tgstk/libmpfr-4.dll
tgstk/tgstk.py
tgstk-0.0.4.dist-info/LICENSE.txt
tgstk-0.0.4.dist-info/METADATA
tgstk-0.0.4.dist-info/WHEEL
tgstk-0.0.4.dist-info/top_level.txt
tgstk-0.0.4.dist-info/RECORD
