Metadata-Version: 2.1
Name: tgstk
Version: 0.0.4
Summary: The Tumour Growth Simulation Toolkit
Home-page: https://github.com/cormarte/tgstk.git
Author: Corentin Martens
Author-email: corentin.martens@ulb.be
License: GPLv3
Platform: UNKNOWN
Classifier: Programming Language :: Python :: 3
Classifier: License :: OSI Approved :: GNU General Public License v3 (GPLv3)
Classifier: Operating System :: Microsoft :: Windows :: Windows 10
Requires-Python: >=3.8
Requires-Dist: vtk (==9.0.2)
